.gitattributes
.gitignore
CHANGELOG.rst
LICENSE
README.md
default.nix
setup.py
shell.nix
.github/workflows/doc.yml
.github/workflows/pypi.yml
.github/workflows/test.yml
doc/Makefile
doc/source/api.rst
doc/source/changelog.rst
doc/source/conf.py
doc/source/index.rst
doc/source/motivation.rst
doc/source/overview.rst
doc/source/_static/.gitkeep
doc/source/_templates/autosummary/class.rst
doc/source/_templates/autosummary/module.rst
haskpy/__init__.py
haskpy/_meta.py
haskpy/autoclass.py
haskpy/conftest.py
haskpy/internal.py
haskpy/optics.py
haskpy/testing.py
haskpy/utils.py
haskpy.egg-info/PKG-INFO
haskpy.egg-info/SOURCES.txt
haskpy.egg-info/dependency_links.txt
haskpy.egg-info/requires.txt
haskpy.egg-info/top_level.txt
haskpy/tests/test_optics.py
haskpy/tests/test_utils.py
haskpy/typeclasses/__init__.py
haskpy/typeclasses/_applicative.py
haskpy/typeclasses/_apply.py
haskpy/typeclasses/_bind.py
haskpy/typeclasses/_cartesian.py
haskpy/typeclasses/_cocartesian.py
haskpy/typeclasses/_contravariant.py
haskpy/typeclasses/_functor.py
haskpy/typeclasses/_monad.py
haskpy/typeclasses/_monoid.py
haskpy/typeclasses/_profunctor.py
haskpy/typeclasses/_semigroup.py
haskpy/typeclasses/applicative.py
haskpy/typeclasses/apply_.py
haskpy/typeclasses/bifunctor.py
haskpy/typeclasses/bind_.py
haskpy/typeclasses/cartesian.py
haskpy/typeclasses/cocartesian.py
haskpy/typeclasses/contravariant.py
haskpy/typeclasses/equality.py
haskpy/typeclasses/foldable.py
haskpy/typeclasses/functor.py
haskpy/typeclasses/hashable.py
haskpy/typeclasses/monad.py
haskpy/typeclasses/monoid.py
haskpy/typeclasses/monoidal.py
haskpy/typeclasses/ord.py
haskpy/typeclasses/profunctor.py
haskpy/typeclasses/readable.py
haskpy/typeclasses/semigroup.py
haskpy/typeclasses/show.py
haskpy/typeclasses/traversable.py
haskpy/typeclasses/typeclass.py
haskpy/types/__init__.py
haskpy/types/compose.py
haskpy/types/constant.py
haskpy/types/dictionary.py
haskpy/types/either.py
haskpy/types/function.py
haskpy/types/hypothesis.py
haskpy/types/identity.py
haskpy/types/io.py
haskpy/types/linkedlist.py
haskpy/types/list.py
haskpy/types/maybe.py
haskpy/types/monoids.py
