Metadata-Version: 2.1
Name: haskpy
Version: 0.3.0
Summary: Utilities inspired by Haskell and Hask category
Home-page: UNKNOWN
Author: Jaakko Luttinen
Author-email: jaakko.luttinen@iki.fi
License: UNKNOWN
Project-URL: Homepage, https://github.com/jluttine/haskpy
Project-URL: Download, https://pypi.org/project/haskpy/
Project-URL: Documentation, https://jluttine.github.io/haskpy/
Project-URL: Bug reports, https://github.com/jluttine/haskpy/issues
Project-URL: Contributing, https://github.com/jluttine/haskpy/pulls
Project-URL: Forum, https://github.com/jluttine/haskpy/discussions
Keywords: functional programming,category theory,Hask category,Haskell,functor,applicative,monad,monoid
Platform: UNKNOWN
Classifier: Programming Language :: Python :: 3 :: Only
Classifier: Development Status :: 3 - Alpha
Classifier: Environment :: Console
Classifier: Intended Audience :: Developers
Classifier: License :: OSI Approved :: MIT License
Classifier: Operating System :: OS Independent
Classifier: Programming Language :: Python :: 3 :: Only
Classifier: Topic :: Scientific/Engineering
Classifier: Topic :: Software Development :: Libraries
Provides-Extra: dev
Provides-Extra: doc
